rl_replicas/__init__.py
rl_replicas/evaluator.py
rl_replicas/experience.py
rl_replicas/metrics_manager.py
rl_replicas/q_function.py
rl_replicas/replay_buffer.py
rl_replicas/utils.py
rl_replicas/value_function.py
rl_replicas/algorithms/__init__.py
rl_replicas/algorithms/ddpg.py
rl_replicas/algorithms/ppo.py
rl_replicas/algorithms/td3.py
rl_replicas/algorithms/trpo.py
rl_replicas/algorithms/vpg.py
rl_replicas/networks/__init__.py
rl_replicas/networks/mlp.py
rl_replicas/optimizers/__init__.py
rl_replicas/optimizers/conjugate_gradient_optimizer.py
rl_replicas/policies/__init__.py
rl_replicas/policies/categorical_policy.py
rl_replicas/policies/deterministic_policy.py
rl_replicas/policies/gaussian_policy.py
rl_replicas/policies/policy.py
rl_replicas/policies/random_policy.py
rl_replicas/policies/stochastic_policy.py
rl_replicas/samplers/__init__.py
rl_replicas/samplers/batch_sampler.py
rl_replicas/samplers/sampler.py
rl_replicas-0.0.7.dist-info/LICENSE
rl_replicas-0.0.7.dist-info/METADATA
rl_replicas-0.0.7.dist-info/WHEEL
rl_replicas-0.0.7.dist-info/top_level.txt
rl_replicas-0.0.7.dist-info/RECORD
