Metadata-Version: 2.1
Name: rl-replicas
Version: 0.0.7
Summary: Reinforcement Learning Replications is a set of Pytorch implementations of reinforcement learning algorithms.
Author: Yamato Kataoka
Project-URL: Homepage, https://github.com/yamatokataoka/reinforcement-learning-replications
Keywords: rl_replicas,reinforcement learning,deep learning,pytorch
Classifier: Development Status :: 4 - Beta
Classifier: Intended Audience :: Developers
Classifier: Intended Audience :: Education
Classifier: Intended Audience :: Science/Research
Classifier: License :: OSI Approved :: MIT License
Classifier: Programming Language :: Python :: 3
Classifier: Topic :: Scientific/Engineering :: Artificial Intelligence
Classifier: Topic :: Software Development :: Libraries
Requires-Python: ~=3.10
License-File: LICENSE
Requires-Dist: gymnasium~=1.0.0
Requires-Dist: numpy~=2.1.3
Requires-Dist: scipy~=1.14.1
Requires-Dist: tensorboard~=2.18.0
Requires-Dist: torch~=2.5.1
